somadorcompleto.v
// implemente um módulo somador de 4 bits

// module somadorcompleto (
//     input [4:0] A,
//     input [4:0] B,
//     input Cin,
//     output [4:0] S,
//     output Cout

// );
//     // interconexão no módulo
//     wire [4:0] S;
//     wire Cout;

//     // Soma de bits e cálculo
//     assign {Cout, S} = A + B + Cin;

// endmodule

module somadorcompleto (a,b,cin,s,cout);
    input a,b,cin;
    output s,cout;

    assign s = a ^ b ^ cin;
    assign cout = (a & b) | (a & cin) | (b & cin);
endmodule

somadorcompleto_tb.v
`include "somadorcompleto.v"
`timescale 1ns/100ps

module somadorcompleto_tb;
    reg a0, b0, ci0;
    wire s0, co0;

    // instanciação do módulo e nomeação por uut
    // delimitação de onde as saídas vão ser ligadas (a quais registradores e fios)
    somadorcompleto uut (.a(a0), .b(b0), .cin(ci0), .s(s0), .cout(co0));

    initial begin
        // diretiva que diz onde o arquivo de dump vai ser criado (.vcd é a extensão padrão)
        $dumpfile("somadorcompleto_tb.vcd");
        // diretiva que diz quais variáveis vão ser monitoradas, 0 significa que você quer salvar variáveis de todos os módulos (entrada e saída)
        // segundo parâmetro é o módulo onde as variáveis serão salvas
        $dumpvars(0, somadorcompleto_tb);
            a0 = 0; b0 = 0; ci0 = 0;
        //#10 significa que após 10 unidades de tempo será realizada a próxima etapa
        #10; a0 = 0; b0 = 0; ci0 = 1;
        #10; a0 = 0; b0 = 1; ci0 = 0;
        #10; a0 = 0; b0 = 1; ci0 = 1;
        #10; a0 = 1; b0 = 0; ci0 = 0;
        #10; a0 = 1; b0 = 0; ci0 = 1;
        #10; a0 = 1; b0 = 1; ci0 = 0;
        #10; a0 = 1; b0 = 1; ci0 = 1;
        #10 $finish;
    end
endmodule

somadorcompleto_tb.vcd
$date
	Wed Dec 11 16:43:30 2024
$end
$version
	Icarus Verilog
$end
$timescale
	100ps
$end
$scope module somadorcompleto_tb $end
$var wire 1 ! s0 $end
$var wire 1 " co0 $end
$var reg 1 # a0 $end
$var reg 1 $ b0 $end
$var reg 1 % ci0 $end
$scope module uut $end
$var wire 1 # a $end
$var wire 1 $ b $end
$var wire 1 % cin $end
$var wire 1 " cout $end
$var wire 1 ! s $end
$upscope $end
$upscope $end
$enddefinitions $end
$comment Show the parameter values. $end
$dumpall
$end
#0
$dumpvars
0%
0$
0#
0"
0!
$end
#100
1!
1%
#200
0%
1$
#300
1"
0!
1%
#400
0"
1!
0%
0$
1#
#500
1"
0!
1%
#600
0%
1$
#700
1!
1%
