verilog-ula/ula_sim.v
module mux8x1_4b (i0, i1, i2, i3, i4, i5, i6, i7, s0, s1, s2, f);
    input [3:0] i0, i1, i2, i3, i4, i5, i6, i7;
    input [2:0] s0, s1, s2;
    output [3:0] f;

    assign f[3] = ~s2&(~s1)&(~s0)&i0[3] | ~s2&(~s1)&s0&i1[3] | ~s2&s1&(~s0)&i2[3] | ~s2&s1&s0&i3[3] | s2&(~s1)&(~s0)&i4[3] | s2&(~s1)&s0&i5[3] | s2&s1&(~s0)&i6[3] | s2&s1&s0&i7[3];
    assign f[2] = ~s2&(~s1)&(~s0)&i0[2] | ~s2&(~s1)&s0&i1[2] | ~s2&s1&(~s0)&i2[2] | ~s2&s1&s0&i3[2] | s2&(~s1)&(~s0)&i4[2] | s2&(~s1)&s0&i5[2] | s2&s1&(~s0)&i6[2] | s2&s1&s0&i7[2];
    assign f[1] = ~s2&(~s1)&(~s0)&i0[1] | ~s2&(~s1)&s0&i1[1] | ~s2&s1&(~s0)&i2[1] | ~s2&s1&s0&i3[1] | s2&(~s1)&(~s0)&i4[1] | s2&(~s1)&s0&i5[1] | s2&s1&(~s0)&i6[1] | s2&s1&s0&i7[1];
    assign f[0] = ~s2&(~s1)&(~s0)&i0[0] | ~s2&(~s1)&s0&i1[0] | ~s2&s1&(~s0)&i2[0] | ~s2&s1&s0&i3[0] | s2&(~s1)&(~s0)&i4[0] | s2&(~s1)&s0&i5[0] | s2&s1&(~s0)&i6[0] | s2&s1&s0&i7[0];
endmodule

module ula (a, b, x, y, z, S);
    input [3:0] a, b;
    input [2:0] x, y, z; // Expanded to 3 bits
    output [3:0] S;

    wire [3:0] w0, w1, w2, w3, w4, w5, w6, w7;

    // ADD, SUB, NOT, NAND, XOR, OR, AND
    assign w0 = a + b;
    assign w1 = a - b;
    assign w2 = a << b;
    assign w3 = a >> b;
    assign w4 = a & b;
    assign w5 = a | b;
    assign w6 = a ^ b;
    assign w7 = ~a;

    mux8x1_4b muxout (.i0(w0), .i1(w1), .i2(w2), .i3(w3),
                      .i4(w4), .i5(w5), .i6(w6), .i7(w7), 
                      .s0(x), .s1(y), .s2(z), .f(S));
endmodule


`timescale 1ns/1ps

module ula_tb;

    // Declaração dos sinais
    reg [3:0] a, b;
    reg [2:0] x, y, z; // Expandido para 3 bits
    wire [3:0] S;

    // Instancia o módulo ULA
    ula dut (
        .a(a),
        .b(b),
        .x(x),
        .y(y),
        .z(z),
        .S(S)
    );

    // Testbench
    integer i, j, k;
    initial begin
        $display("Starting testbench for ULA...");

        // Configuração do dumpfile para o gtkwave
        $dumpfile("ula_tb.vcd"); // Gera o arquivo .vcd
        $dumpvars(0, ula_tb);    // Registra todos os sinais do módulo de teste

        // Inicializa entradas
        a = 0; b = 0; x = 0; y = 0; z = 0;

        // Gera todas as combinações exaustivas
        for (i = 0; i < 16; i = i + 1) begin
            for (j = 0; j < 16; j = j + 1) begin
                for (k = 0; k < 8; k = k + 1) begin
                    a = i; 
                    b = j;
                    {x, y, z} = k; // Atribui 3 bits para x, y e z

                    #10;

                    $display("a=%b, b=%b, x=%b, y=%b, z=%b --> S=%b", a, b, x, y, z, S);
                end
            end
        end

        $display("Testbench completed.");
        $finish;
    end

endmodule

verilog-ula/ula_tb.vcd
$date
	Tue Dec 17 13:25:40 2024
$end
$version
	Icarus Verilog
$end
$timescale
	1ps
$end
$scope module ula_tb $end
$var wire 4 ! S [3:0] $end
$var reg 4 " a [3:0] $end
$var reg 4 # b [3:0] $end
$var reg 3 $ x [2:0] $end
$var reg 3 % y [2:0] $end
$var reg 3 & z [2:0] $end
$var integer 32 ' i [31:0] $end
$var integer 32 ( j [31:0] $end
$var integer 32 ) k [31:0] $end
$scope module dut $end
$var wire 4 * a [3:0] $end
$var wire 4 + b [3:0] $end
$var wire 4 , w4 [3:0] $end
$var wire 4 - w5 [3:0] $end
$var wire 4 . w6 [3:0] $end
$var wire 4 / w7 [3:0] $end
$var wire 3 0 x [2:0] $end
$var wire 3 1 y [2:0] $end
$var wire 3 2 z [2:0] $end
$var wire 4 3 w3 [3:0] $end
$var wire 4 4 w2 [3:0] $end
$var wire 4 5 w1 [3:0] $end
$var wire 4 6 w0 [3:0] $end
$var wire 4 7 S [3:0] $end
$scope module muxout $end
$var wire 4 8 i0 [3:0] $end
$var wire 4 9 i1 [3:0] $end
$var wire 4 : i2 [3:0] $end
$var wire 4 ; i3 [3:0] $end
$var wire 4 < i4 [3:0] $end
$var wire 4 = i5 [3:0] $end
$var wire 4 > i6 [3:0] $end
$var wire 4 ? i7 [3:0] $end
$var wire 3 @ s0 [2:0] $end
$var wire 3 A s1 [2:0] $end
$var wire 3 B s2 [2:0] $end
$var wire 4 C f [3:0] $end
$upscope $end
$upscope $end
$upscope $end
$enddefinitions $end
$comment Show the parameter values. $end
$dumpall
$end
#0
$dumpvars
b0 C
b0 B
b0 A
b0 @
b1111 ?
b0 >
b0 =
b0 <
b0 ;
b0 :
b0 9
b0 8
b0 7
b0 6
b0 5
b0 4
b0 3
b0 2
b0 1
b0 0
b1111 /
b0 .
b0 -
b0 ,
b0 +
b0 *
b0 )
b0 (
b0 '
b0 &
b0 %
b0 $
b0 #
b0 "
b0 !
$end
#10000
b1 &
b1 2
b1 B
b1 )
#20000
b10 &
b10 2
b10 B
b10 )
#30000
b11 &
b11 2
b11 B
b11 )
#40000
b100 &
b100 2
b100 B
b100 )
#50000
b101 &
b101 2
b101 B
b101 )
#60000
b110 &
b110 2
b110 B
b110 )
#70000
b111 &
b111 2
b111 B
b111 )
#80000
b1 !
b1 7
b1 C
b1 -
b1 =
b1 .
b1 >
b0 &
b0 2
b0 B
b1 6
b1 8
b1111 5
b1111 9
b1 #
b1 +
b1 (
b0 )
#90000
b0 !
b0 7
b0 C
b1 &
b1 2
b1 B
b1 )
#100000
b1 !
b1 7
b1 C
b10 &
b10 2
b10 B
b10 )
#110000
b0 !
b0 7
b0 C
b11 &
b11 2
b11 B
b11 )
#120000
b1 !
b1 7
b1 C
b100 &
b100 2
b100 B
b100 )
#130000
b0 !
b0 7
b0 C
b101 &
b101 2
b101 B
b101 )
#140000
b1 !
b1 7
b1 C
b110 &
b110 2
b110 B
b110 )
#150000
b0 !
b0 7
b0 C
b111 &
b111 2
b111 B
b111 )
#160000
b10 !
b10 7
b10 C
b10 -
b10 =
b10 .
b10 >
b0 &
b0 2
b0 B
b10 6
b10 8
b1110 5
b1110 9
b10 #
b10 +
b10 (
b0 )
#170000
b0 !
b0 7
b0 C
b1 &
b1 2
b1 B
b1 )
#180000
b10 !
b10 7
b10 C
b10 &
b10 2
b10 B
b10 )
#190000
b0 !
b0 7
b0 C
b11 &
b11 2
b11 B
b11 )
#200000
b10 !
b10 7
b10 C
b100 &
b100 2
b100 B
b100 )
#210000
b0 !
b0 7
b0 C
b101 &
b101 2
b101 B
b101 )
#220000
b10 !
b10 7
b10 C
b110 &
b110 2
b110 B
b110 )
#230000
b0 !
b0 7
b0 C
b111 &
b111 2
b111 B
b111 )
#240000
b11 !
b11 7
b11 C
b11 -
b11 =
b11 .
b11 >
b0 &
b0 2
b0 B
b11 6
b11 8
b1101 5
b1101 9
b11 #
b11 +
b11 (
b0 )
#250000
b0 !
b0 7
b0 C
b1 &
b1 2
b1 B
b1 )
#260000
b11 !
b11 7
b11 C
b10 &
b10 2
b10 B
b10 )
#270000
b0 !
b0 7
b0 C
b11 &
b11 2
b11 B
b11 )
#280000
b11 !
b11 7
b11 C
b100 &
b100 2
b100 B
b100 )
#290000
b0 !
b0 7
b0 C
b101 &
b101 2
b101 B
b101 )
#300000
b11 !
b11 7
b11 C
b110 &
b110 2
b110 B
b110 )
#310000
b0 !
b0 7
b0 C
b111 &
b111 2
b111 B
b111 )
#320000
b100 !
b100 7
b100 C
b100 -
b100 =
b100 .
b100 >
b0 &
b0 2
b0 B
b100 6
b100 8
b1100 5
b1100 9
b100 #
b100 +
b100 (
b0 )
#330000
b0 !
b0 7
b0 C
b1 &
b1 2
b1 B
b1 )
#340000
b100 !
b100 7
b100 C
b10 &
b10 2
b10 B
b10 )
#350000
b0 !
b0 7
b0 C
b11 &
b11 2
b11 B
b11 )
#360000
b100 !
b100 7
b100 C
b100 &
b100 2
b100 B
b100 )
#370000
b0 !
b0 7
b0 C
b101 &
b101 2
b101 B
b101 )
#380000
b100 !
b100 7
b100 C
b110 &
b110 2
b110 B
b110 )
#390000
b0 !
b0 7
b0 C
b111 &
b111 2
b111 B
b111 )
#400000
b101 !
b101 7
b101 C
b101 -
b101 =
b101 .
b101 >
b0 &
b0 2
b0 B
b101 6
b101 8
b1011 5
b1011 9
b101 #
b101 +
b101 (
b0 )
#410000
b0 !
b0 7
b0 C
b1 &
b1 2
b1 B
b1 )
#420000
b101 !
b101 7
b101 C
b10 &
b10 2
b10 B
b10 )
#430000
b0 !
b0 7
b0 C
b11 &
b11 2
b11 B
b11 )
#440000
b101 !
b101 7
b101 C
b100 &
b100 2
b100 B
b100 )
#450000
b0 !
b0 7
b0 C
b101 &
b101 2
b101 B
b101 )
#460000
b101 !
b101 7
b101 C
b110 &
b110 2
b110 B
b110 )
#470000
b0 !
b0 7
b0 C
b111 &
b111 2
b111 B
b111 )
#480000
b110 !
b110 7
b110 C
b110 -
b110 =
b110 .
b110 >
b0 &
b0 2
b0 B
b110 6
b110 8
b1010 5
b1010 9
b110 #
b110 +
b110 (
b0 )
#490000
b0 !
b0 7
b0 C
b1 &
b1 2
b1 B
b1 )
#500000
b110 !
b110 7
b110 C
b10 &
b10 2
b10 B
b10 )
#510000
b0 !
b0 7
b0 C
b11 &
b11 2
b11 B
b11 )
#520000
b110 !
b110 7
b110 C
b100 &
b100 2
b100 B
b100 )
#530000
b0 !
b0 7
b0 C
b101 &
b101 2
b101 B
b101 )
#540000
b110 !
b110 7
b110 C
b110 &
b110 2
b110 B
b110 )
#550000
b0 !
b0 7
b0 C
b111 &
b111 2
b111 B
b111 )
#560000
b111 !
b111 7
b111 C
b111 -
b111 =
b111 .
b111 >
b0 &
b0 2
b0 B
b111 6
b111 8
b1001 5
b1001 9
b111 #
b111 +
b111 (
b0 )
#570000
b0 !
b0 7
b0 C
b1 &
b1 2
b1 B
b1 )
#580000
b111 !
b111 7
b111 C
b10 &
b10 2
b10 B
b10 )
#590000
b0 !
b0 7
b0 C
b11 &
b11 2
b11 B
b11 )
#600000
b111 !
b111 7
b111 C
b100 &
b100 2
b100 B
b100 )
#610000
b0 !
b0 7
b0 C
b101 &
b101 2
b101 B
b101 )
#620000
b111 !
b111 7
b111 C
b110 &
b110 2
b110 B
b110 )
#630000
b0 !
b0 7
b0 C
b111 &
b111 2
b111 B
b111 )
#640000
b1000 !
b1000 7
b1000 C
b1000 -
b1000 =
b1000 .
b1000 >
b0 &
b0 2
b0 B
b1000 6
b1000 8
b1000 5
b1000 9
b1000 #
b1000 +
b1000 (
b0 )
#650000
b0 !
b0 7
b0 C
b1 &
b1 2
b1 B
b1 )
#660000
b1000 !
b1000 7
b1000 C
b10 &
b10 2
b10 B
b10 )
#670000
b0 !
b0 7
b0 C
b11 &
b11 2
b11 B
b11 )
#680000
b1000 !
b1000 7
b1000 C
b100 &
b100 2
b100 B
b100 )
#690000
b0 !
b0 7
b0 C
b101 &
b101 2
b101 B
b101 )
#700000
b1000 !
b1000 7
b1000 C
b110 &
b110 2
b110 B
b110 )
#710000
b0 !
b0 7
b0 C
b111 &
b111 2
b111 B
b111 )
#720000
b1001 !
b1001 7
b1001 C
b1001 -
b1001 =
b1001 .
b1001 >
b0 &
b0 2
b0 B
b1001 6
b1001 8
b111 5
b111 9
b1001 #
b1001 +
b1001 (
b0 )
#730000
b0 !
b0 7
b0 C
b1 &
b1 2
b1 B
b1 )
#740000
b1001 !
b1001 7
b1001 C
b10 &
b10 2
b10 B
b10 )
#750000
b0 !
b0 7
b0 C
b11 &
b11 2
b11 B
b11 )
#760000
b1001 !
b1001 7
b1001 C
b100 &
b100 2
b100 B
b100 )
#770000
b0 !
b0 7
b0 C
b101 &
b101 2
b101 B
b101 )
#780000
b1001 !
b1001 7
b1001 C
b110 &
b110 2
b110 B
b110 )
#790000
b0 !
b0 7
b0 C
b111 &
b111 2
b111 B
b111 )
#800000
b1010 !
b1010 7
b1010 C
b1010 -
b1010 =
b1010 .
b1010 >
b0 &
b0 2
b0 B
b1010 6
b1010 8
b110 5
b110 9
b1010 #
b1010 +
b1010 (
b0 )
#810000
b0 !
b0 7
b0 C
b1 &
b1 2
b1 B
b1 )
#820000
b1010 !
b1010 7
b1010 C
b10 &
b10 2
b10 B
b10 )
#830000
b0 !
b0 7
b0 C
b11 &
b11 2
b11 B
b11 )
#840000
b1010 !
b1010 7
b1010 C
b100 &
b100 2
b100 B
b100 )
#850000
b0 !
b0 7
b0 C
b101 &
b101 2
b101 B
b101 )
#860000
b1010 !
b1010 7
b1010 C
b110 &
b110 2
b110 B
b110 )
#870000
b0 !
b0 7
b0 C
b111 &
b111 2
b111 B
b111 )
#880000
b1011 !
b1011 7
b1011 C
b1011 -
b1011 =
b1011 .
b1011 >
b0 &
b0 2
b0 B
b1011 6
b1011 8
b101 5
b101 9
b1011 #
b1011 +
b1011 (
b0 )
#890000
b0 !
b0 7
b0 C
b1 &
b1 2
b1 B
b1 )
#900000
b1011 !
b1011 7
b1011 C
b10 &
b10 2
b10 B
b10 )
#910000
b0 !
b0 7
b0 C
b11 &
b11 2
b11 B
b11 )
#920000
b1011 !
b1011 7
b1011 C
b100 &
b100 2
b100 B
b100 )
#930000
b0 !
b0 7
b0 C
b101 &
b101 2
b101 B
b101 )
#940000
b1011 !
b1011 7
b1011 C
b110 &
b110 2
b110 B
b110 )
#950000
b0 !
b0 7
b0 C
b111 &
b111 2
b111 B
b111 )
#960000
b1100 !
b1100 7
b1100 C
b1100 -
b1100 =
b1100 .
b1100 >
b0 &
b0 2
b0 B
b1100 6
b1100 8
b100 5
b100 9
b1100 #
b1100 +
b1100 (
b0 )
#970000
b0 !
b0 7
b0 C
b1 &
b1 2
b1 B
b1 )
#980000
b1100 !
b1100 7
b1100 C
b10 &
b10 2
b10 B
b10 )
#990000
b0 !
b0 7
b0 C
b11 &
b11 2
b11 B
b11 )
#1000000
b1100 !
b1100 7
b1100 C
b100 &
b100 2
b100 B
b100 )
#1010000
b0 !
b0 7
b0 C
b101 &
b101 2
b101 B
b101 )
#1020000
b1100 !
b1100 7
b1100 C
b110 &
b110 2
b110 B
b110 )
#1030000
b0 !
b0 7
b0 C
b111 &
b111 2
b111 B
b111 )
#1040000
b1101 !
b1101 7
b1101 C
b1101 -
b1101 =
b1101 .
b1101 >
b0 &
b0 2
b0 B
b1101 6
b1101 8
b11 5
b11 9
b1101 #
b1101 +
b1101 (
b0 )
#1050000
b0 !
b0 7
b0 C
b1 &
b1 2
b1 B
b1 )
#1060000
b1101 !
b1101 7
b1101 C
b10 &
b10 2
b10 B
b10 )
#1070000
b0 !
b0 7
b0 C
b11 &
b11 2
b11 B
b11 )
#1080000
b1101 !
b1101 7
b1101 C
b100 &
b100 2
b100 B
b100 )
#1090000
b0 !
b0 7
b0 C
b101 &
b101 2
b101 B
b101 )
#1100000
b1101 !
b1101 7
b1101 C
b110 &
b110 2
b110 B
b110 )
#1110000
b0 !
b0 7
b0 C
b111 &
b111 2
b111 B
b111 )
#1120000
b1110 !
b1110 7
b1110 C
b1110 -
b1110 =
b1110 .
b1110 >
b0 &
b0 2
b0 B
b1110 6
b1110 8
b10 5
b10 9
b1110 #
b1110 +
b1110 (
b0 )
#1130000
b0 !
b0 7
b0 C
b1 &
b1 2
b1 B
b1 )
#1140000
b1110 !
b1110 7
b1110 C
b10 &
b10 2
b10 B
b10 )
#1150000
b0 !
b0 7
b0 C
b11 &
b11 2
b11 B
b11 )
#1160000
b1110 !
b1110 7
b1110 C
b100 &
b100 2
b100 B
b100 )
#1170000
b0 !
b0 7
b0 C
b101 &
b101 2
b101 B
b101 )
#1180000
b1110 !
b1110 7
b1110 C
b110 &
b110 2
b110 B
b110 )
#1190000
b0 !
b0 7
b0 C
b111 &
b111 2
b111 B
b111 )
#1200000
b1111 !
b1111 7
b1111 C
b1111 -
b1111 =
b1111 .
b1111 >
b0 &
b0 2
b0 B
b1111 6
b1111 8
b1 5
b1 9
b1111 #
b1111 +
b1111 (
b0 )
#1210000
b0 !
b0 7
b0 C
b1 &
b1 2
b1 B
b1 )
#1220000
b1111 !
b1111 7
b1111 C
b10 &
b10 2
b10 B
b10 )
#1230000
b0 !
b0 7
b0 C
b11 &
b11 2
b11 B
b11 )
#1240000
b1111 !
b1111 7
b1111 C
b100 &
b100 2
b100 B
b100 )
#1250000
b0 !
b0 7
b0 C
b101 &
b101 2
b101 B
b101 )
#1260000
b1111 !
b1111 7
b1111 C
b110 &
b110 2
b110 B
b110 )
#1270000
b0 !
b0 7
b0 C
b111 &
b111 2
b111 B
b111 )
#1280000
b1 !
b1 7
b1 C
b1 -
b1 =
b1 .
b1 >
b1110 /
b1110 ?
b0 &
b0 2
b0 B
b1 4
b1 :
b1 3
b1 ;
b0 #
b0 +
b1 6
b1 8
b1 5
b1 9
b1 "
b1 *
b1 '
b0 (
b0 )
#1290000
b0 !
b0 7
b0 C
b1 &
b1 2
b1 B
b1 )
#1300000
b1 !
b1 7
b1 C
b10 &
b10 2
b10 B
b10 )
#1310000
b0 !
b0 7
b0 C
b11 &
b11 2
b11 B
b11 )
#1320000
b1 !
b1 7
b1 C
b100 &
b100 2
b100 B
b100 )
#1330000
b0 !
b0 7
b0 C
b101 &
b101 2
b101 B
b101 )
#1340000
b1 !
b1 7
b1 C
b110 &
b110 2
b110 B
b110 )
#1350000
b0 !
b0 7
b0 C
b111 &
b111 2
b111 B
b111 )
#1360000
b10 !
b10 7
b10 C
b1 ,
b1 <
b0 .
b0 >
b0 &
b0 2
b0 B
b10 6
b10 8
b0 5
b0 9
b10 4
b10 :
b0 3
b0 ;
b1 #
b1 +
b1 (
b0 )
#1370000
b1 !
b1 7
b1 C
b1 &
b1 2
b1 B
b1 )
#1380000
b10 !
b10 7
b10 C
b10 &
b10 2
b10 B
b10 )
#1390000
b1 !
b1 7
b1 C
b11 &
b11 2
b11 B
b11 )
#1400000
b10 !
b10 7
b10 C
b100 &
b100 2
b100 B
b100 )
#1410000
b1 !
b1 7
b1 C
b101 &
b101 2
b101 B
b101 )
#1420000
b10 !
b10 7
b10 C
b110 &
b110 2
b110 B
b110 )
#1430000
b1 !
b1 7
b1 C
b111 &
b111 2
b111 B
b111 )
#1440000
b11 !
b11 7
b11 C
b0 ,
b0 <
b11 -
b11 =
b11 .
b11 >
b0 &
b0 2
b0 B
b11 6
b11 8
b1111 5
b1111 9
b100 4
b100 :
b10 #
b10 +
b10 (
b0 )
#1450000
b0 !
b0 7
b0 C
b1 &
b1 2
b1 B
b1 )
#1460000
b11 !
b11 7
b11 C
b10 &
b10 2
b10 B
b10 )
#1470000
b0 !
b0 7
b0 C
b11 &
b11 2
b11 B
b11 )
#1480000
b11 !
b11 7
b11 C
b100 &
b100 2
b100 B
b100 )
#1490000
b0 !
b0 7
b0 C
b101 &
b101 2
b101 B
b101 )
#1500000
b11 !
b11 7
b11 C
b110 &
b110 2
b110 B
b110 )
#1510000
b0 !
b0 7
b0 C
b111 &
b111 2
b111 B
b111 )
#1520000
b100 !
b100 7
b100 C
b1 ,
b1 <
b10 .
b10 >
b0 &
b0 2
b0 B
b100 6
b100 8
b1110 5
b1110 9
b1000 4
b1000 :
b11 #
b11 +
b11 (
b0 )
#1530000
b1 !
b1 7
b1 C
b1 &
b1 2
b1 B
b1 )
#1540000
b100 !
b100 7
b100 C
b10 &
b10 2
b10 B
b10 )
#1550000
b1 !
b1 7
b1 C
b11 &
b11 2
b11 B
b11 )
#1560000
b100 !
b100 7
b100 C
b100 &
b100 2
b100 B
b100 )
#1570000
b1 !
b1 7
b1 C
b101 &
b101 2
b101 B
b101 )
#1580000
b100 !
b100 7
b100 C
b110 &
b110 2
b110 B
b110 )
#1590000
b1 !
b1 7
b1 C
b111 &
b111 2
b111 B
b111 )
#1600000
b101 !
b101 7
b101 C
b0 ,
b0 <
b101 -
b101 =
b101 .
b101 >
b0 &
b0 2
b0 B
b101 6
b101 8
b1101 5
b1101 9
b0 4
b0 :
b100 #
b100 +
b100 (
b0 )
#1610000
b0 !
b0 7
b0 C
b1 &
b1 2
b1 B
b1 )
#1620000
b101 !
b101 7
b101 C
b10 &
b10 2
b10 B
b10 )
#1630000
b0 !
b0 7
b0 C
b11 &
b11 2
b11 B
b11 )
#1640000
b101 !
b101 7
b101 C
b100 &
b100 2
b100 B
b100 )
#1650000
b0 !
b0 7
b0 C
b101 &
b101 2
b101 B
b101 )
#1660000
b101 !
b101 7
b101 C
b110 &
b110 2
b110 B
b110 )
#1670000
b0 !
b0 7
b0 C
b111 &
b111 2
b111 B
b111 )
#1680000
b110 !
b110 7
b110 C
b1 ,
b1 <
b100 .
b100 >
b0 &
b0 2
b0 B
b110 6
b110 8
b1100 5
b1100 9
b101 #
b101 +
b101 (
b0 )
#1690000
b1 !
b1 7
b1 C
b1 &
b1 2
b1 B
b1 )
#1700000
b110 !
b110 7
b110 C
b10 &
b10 2
b10 B
b10 )
#1710000
b1 !
b1 7
b1 C
b11 &
b11 2
b11 B
b11 )
#1720000
b110 !
b110 7
b110 C
b100 &
b100 2
b100 B
b100 )
#1730000
b1 !
b1 7
b1 C
b101 &
b101 2
b101 B
b101 )
#1740000
b110 !
b110 7
b110 C
b110 &
b110 2
b110 B
b110 )
#1750000
b1 !
b1 7
b1 C
b111 &
b111 2
b111 B
b111 )
#1760000
b111 !
b111 7
b111 C
b0 ,
b0 <
b111 -
b111 =
b111 .
b111 >
b0 &
b0 2
b0 B
b111 6
b111 8
b1011 5
b1011 9
b110 #
b110 +
b110 (
b0 )
#1770000
b0 !
b0 7
b0 C
b1 &
b1 2
b1 B
b1 )
#1780000
b111 !
b111 7
b111 C
b10 &
b10 2
b10 B
b10 )
#1790000
b0 !
b0 7
b0 C
b11 &
b11 2
b11 B
b11 )
#1800000
b111 !
b111 7
b111 C
b100 &
b100 2
b100 B
b100 )
#1810000
b0 !
b0 7
b0 C
b101 &
b101 2
b101 B
b101 )
#1820000
b111 !
b111 7
b111 C
b110 &
b110 2
b110 B
b110 )
#1830000
b0 !
b0 7
b0 C
b111 &
b111 2
b111 B
b111 )
#1840000
b1000 !
b1000 7
b1000 C
b1 ,
b1 <
b110 .
b110 >
b0 &
b0 2
b0 B
b1000 6
b1000 8
b1010 5
b1010 9
b111 #
b111 +
b111 (
b0 )
#1850000
b1 !
b1 7
b1 C
b1 &
b1 2
b1 B
b1 )
#1860000
b1000 !
b1000 7
b1000 C
b10 &
b10 2
b10 B
b10 )
#1870000
b1 !
b1 7
b1 C
b11 &
b11 2
b11 B
b11 )
#1880000
b1000 !
b1000 7
b1000 C
b100 &
b100 2
b100 B
b100 )
#1890000
b1 !
b1 7
b1 C
b101 &
b101 2
b101 B
b101 )
#1900000
b1000 !
b1000 7
b1000 C
b110 &
b110 2
b110 B
b110 )
#1910000
b1 !
b1 7
b1 C
b111 &
b111 2
b111 B
b111 )
#1920000
b1001 !
b1001 7
b1001 C
b0 ,
b0 <
b1001 -
b1001 =
b1001 .
b1001 >
b0 &
b0 2
b0 B
b1001 6
b1001 8
b1001 5
b1001 9
b1000 #
b1000 +
b1000 (
b0 )
#1930000
b0 !
b0 7
b0 C
b1 &
b1 2
b1 B
b1 )
#1940000
b1001 !
b1001 7
b1001 C
b10 &
b10 2
b10 B
b10 )
#1950000
b0 !
b0 7
b0 C
b11 &
b11 2
b11 B
b11 )
#1960000
b1001 !
b1001 7
b1001 C
b100 &
b100 2
b100 B
b100 )
#1970000
b0 !
b0 7
b0 C
b101 &
b101 2
b101 B
b101 )
#1980000
b1001 !
b1001 7
b1001 C
b110 &
b110 2
b110 B
b110 )
#1990000
b0 !
b0 7
b0 C
b111 &
b111 2
b111 B
b111 )
#2000000
b1010 !
b1010 7
b1010 C
b1 ,
b1 <
b1000 .
b1000 >
b0 &
b0 2
b0 B
b1010 6
b1010 8
b1000 5
b1000 9
b1001 #
b1001 +
b1001 (
b0 )
#2010000
b1 !
b1 7
b1 C
b1 &
b1 2
b1 B
b1 )
#2020000
b1010 !
b1010 7
b1010 C
b10 &
b10 2
b10 B
b10 )
#2030000
b1 !
b1 7
b1 C
b11 &
b11 2
b11 B
b11 )
#2040000
b1010 !
b1010 7
b1010 C
b100 &
b100 2
b100 B
b100 )
#2050000
b1 !
b1 7
b1 C
b101 &
b101 2
b101 B
b101 )
#2060000
b1010 !
b1010 7
b1010 C
b110 &
b110 2
b110 B
b110 )
#2070000
b1 !
b1 7
b1 C
b111 &
b111 2
b111 B
b111 )
#2080000
b1011 !
b1011 7
b1011 C
b0 ,
b0 <
b1011 -
b1011 =
b1011 .
b1011 >
b0 &
b0 2
b0 B
b1011 6
b1011 8
b111 5
b111 9
b1010 #
b1010 +
b1010 (
b0 )
#2090000
b0 !
b0 7
b0 C
b1 &
b1 2
b1 B
b1 )
#2100000
b1011 !
b1011 7
b1011 C
b10 &
b10 2
b10 B
b10 )
#2110000
b0 !
b0 7
b0 C
b11 &
b11 2
b11 B
b11 )
#2120000
b1011 !
b1011 7
b1011 C
b100 &
b100 2
b100 B
b100 )
#2130000
b0 !
b0 7
b0 C
b101 &
b101 2
b101 B
b101 )
#2140000
b1011 !
b1011 7
b1011 C
b110 &
b110 2
b110 B
b110 )
#2150000
b0 !
b0 7
b0 C
b111 &
b111 2
b111 B
b111 )
#2160000
b1100 !
b1100 7
b1100 C
b1 ,
b1 <
b1010 .
b1010 >
b0 &
b0 2
b0 B
b1100 6
b1100 8
b110 5
b110 9
b1011 #
b1011 +
b1011 (
b0 )
#2170000
b1 !
b1 7
b1 C
b1 &
b1 2
b1 B
b1 )
#2180000
b1100 !
b1100 7
b1100 C
b10 &
b10 2
b10 B
b10 )
#2190000
b1 !
b1 7
b1 C
b11 &
b11 2
b11 B
b11 )
#2200000
b1100 !
b1100 7
b1100 C
b100 &
b100 2
b100 B
b100 )
#2210000
b1 !
b1 7
b1 C
b101 &
b101 2
b101 B
b101 )
#2220000
b1100 !
b1100 7
b1100 C
b110 &
b110 2
b110 B
b110 )
#2230000
b1 !
b1 7
b1 C
b111 &
b111 2
b111 B
b111 )
#2240000
b1101 !
b1101 7
b1101 C
b0 ,
b0 <
b1101 -
b1101 =
b1101 .
b1101 >
b0 &
b0 2
b0 B
b1101 6
b1101 8
b101 5
b101 9
b1100 #
b1100 +
b1100 (
b0 )
#2250000
b0 !
b0 7
b0 C
b1 &
b1 2
b1 B
b1 )
#2260000
b1101 !
b1101 7
b1101 C
b10 &
b10 2
b10 B
b10 )
#2270000
b0 !
b0 7
b0 C
b11 &
b11 2
b11 B
b11 )
#2280000
b1101 !
b1101 7
b1101 C
b100 &
b100 2
b100 B
b100 )
#2290000
b0 !
b0 7
b0 C
b101 &
b101 2
b101 B
b101 )
#2300000
b1101 !
b1101 7
b1101 C
b110 &
b110 2
b110 B
b110 )
#2310000
b0 !
b0 7
b0 C
b111 &
b111 2
b111 B
b111 )
#2320000
b1110 !
b1110 7
b1110 C
b1 ,
b1 <
b1100 .
b1100 >
b0 &
b0 2
b0 B
b1110 6
b1110 8
b100 5
b100 9
b1101 #
b1101 +
b1101 (
b0 )
#2330000
b1 !
b1 7
b1 C
b1 &
b1 2
b1 B
b1 )
#2340000
b1110 !
b1110 7
b1110 C
b10 &
b10 2
b10 B
b10 )
#2350000
b1 !
b1 7
b1 C
b11 &
b11 2
b11 B
b11 )
#2360000
b1110 !
b1110 7
b1110 C
b100 &
b100 2
b100 B
b100 )
#2370000
b1 !
b1 7
b1 C
b101 &
b101 2
b101 B
b101 )
#2380000
b1110 !
b1110 7
b1110 C
b110 &
b110 2
b110 B
b110 )
#2390000
b1 !
b1 7
b1 C
b111 &
b111 2
b111 B
b111 )
#2400000
b1111 !
b1111 7
b1111 C
b0 ,
b0 <
b1111 -
b1111 =
b1111 .
b1111 >
b0 &
b0 2
b0 B
b1111 6
b1111 8
b11 5
b11 9
b1110 #
b1110 +
b1110 (
b0 )
#2410000
b0 !
b0 7
b0 C
b1 &
b1 2
b1 B
b1 )
#2420000
b1111 !
b1111 7
b1111 C
b10 &
b10 2
b10 B
b10 )
#2430000
b0 !
b0 7
b0 C
b11 &
b11 2
b11 B
b11 )
#2440000
b1111 !
b1111 7
b1111 C
b100 &
b100 2
b100 B
b100 )
#2450000
b0 !
b0 7
b0 C
b101 &
b101 2
b101 B
b101 )
#2460000
b1111 !
b1111 7
b1111 C
b110 &
b110 2
b110 B
b110 )
#2470000
b0 !
b0 7
b0 C
b111 &
b111 2
b111 B
b111 )
#2480000
b1 ,
b1 <
b1110 .
b1110 >
b0 &
b0 2
b0 B
b0 6
b0 8
b10 5
b10 9
b1111 #
b1111 +
b1111 (
b0 )
#2490000
b1 !
b1 7
b1 C
b1 &
b1 2
b1 B
b1 )
#2500000
b0 !
b0 7
b0 C
b10 &
b10 2
b10 B
b10 )
#2510000
b1 !
b1 7
b1 C
b11 &
b11 2
b11 B
b11 )
#2520000
b0 !
b0 7
b0 C
b100 &
b100 2
b100 B
b100 )
#2530000
b1 !
b1 7
b1 C
b101 &
b101 2
b101 B
b101 )
#2540000
b0 !
b0 7
b0 C
b110 &
b110 2
b110 B
b110 )
#2550000
b1 !
b1 7
b1 C
b111 &
b111 2
b111 B
b111 )
